kafkaescli/__init__.py
kafkaescli/__main__.py
kafkaescli/constants.py
kafkaescli/core/__init__.py
kafkaescli/core/config/__init__.py
kafkaescli/core/config/models.py
kafkaescli/core/config/services.py
kafkaescli/core/consumer/__init__.py
kafkaescli/core/consumer/models.py
kafkaescli/core/consumer/services.py
kafkaescli/core/middleware/__init__.py
kafkaescli/core/middleware/models.py
kafkaescli/core/middleware/services.py
kafkaescli/core/producer/__init__.py
kafkaescli/core/producer/models.py
kafkaescli/core/producer/services.py
kafkaescli/core/shared/__init__.py
kafkaescli/core/shared/models.py
kafkaescli/core/shared/services.py
kafkaescli/infra/__init__.py
kafkaescli/infra/containers.py
kafkaescli/infra/kafka.py
kafkaescli/infra/webhook.py
kafkaescli/interface/__init__.py
kafkaescli/interface/cli.py
kafkaescli/interface/web/__init__.py
kafkaescli/interface/web/api.py
kafkaescli/interface/web/schemas.py
kafkaescli/lib/__init__.py
kafkaescli/lib/coroutines.py
kafkaescli/lib/results.py
kafkaescli-0.1.11.dist-info/LICENSE
kafkaescli-0.1.11.dist-info/WHEEL
kafkaescli-0.1.11.dist-info/METADATA
kafkaescli-0.1.11.dist-info/RECORD
