Metadata-Version: 2.1
Name: kafkaescli
Version: 0.1.11
Summary: A magical kafka command line interface.
Home-page: https://github.com/jonykalavera/kafkaescli
Author: Jony Kalavera
Author-email: mr.jony@gmail.com
Requires-Python: >=3.9,<4.0
Classifier: Programming Language :: Python :: 3
Classifier: Programming Language :: Python :: 3.10
Classifier: Programming Language :: Python :: 3.9
Requires-Dist: aiohttp (>=3.8.1,<4.0.0)
Requires-Dist: aiokafka (>=0.7.2,<0.8.0)
Requires-Dist: dependency-injector (>=4.39.1,<5.0.0)
Requires-Dist: fastapi (>=0.75.1,<0.76.0)
Requires-Dist: meiga (>=1.3.1,<2.0.0)
Requires-Dist: pydantic (>=1.9.0,<2.0.0)
Requires-Dist: pytest-cov (>=3.0.0,<4.0.0)
Requires-Dist: typer (>=0.4.1,<0.5.0)
Requires-Dist: uvicorn (>=0.17.6,<0.18.0)
Project-URL: Repository, https://github.com/jonykalavera/kafkaescli
